NiukeJavaGongchengshiQiuzhiJingyanFenxiang20212022Fix1/README.md
NiukeJavaGongchengshiQiuzhiJingyanFenxiang20212022Fix1/__init__.py
NiukeJavaGongchengshiQiuzhiJingyanFenxiang20212022Fix1/__main__.py
NiukeJavaGongchengshiQiuzhiJingyanFenxiang20212022Fix1/file.epub
NiukeJavaGongchengshiQiuzhiJingyanFenxiang20212022Fix1/index.html
NiukeJavaGongchengshiQiuzhiJingyanFenxiang20212022Fix1/css/__init__.py
NiukeJavaGongchengshiQiuzhiJingyanFenxiang20212022Fix1/css/annotations.css
NiukeJavaGongchengshiQiuzhiJingyanFenxiang20212022Fix1/css/main.css
NiukeJavaGongchengshiQiuzhiJingyanFenxiang20212022Fix1/css/normalize.css
NiukeJavaGongchengshiQiuzhiJingyanFenxiang20212022Fix1/css/popup.css
NiukeJavaGongchengshiQiuzhiJingyanFenxiang20212022Fix1/font/__init__.py
NiukeJavaGongchengshiQiuzhiJingyanFenxiang20212022Fix1/font/fontello.eot
NiukeJavaGongchengshiQiuzhiJingyanFenxiang20212022Fix1/font/fontello.svg
NiukeJavaGongchengshiQiuzhiJingyanFenxiang20212022Fix1/font/fontello.ttf
NiukeJavaGongchengshiQiuzhiJingyanFenxiang20212022Fix1/font/fontello.woff
NiukeJavaGongchengshiQiuzhiJingyanFenxiang20212022Fix1/img/__init__.py
NiukeJavaGongchengshiQiuzhiJingyanFenxiang20212022Fix1/img/annotator-glyph-sprite.png
NiukeJavaGongchengshiQiuzhiJingyanFenxiang20212022Fix1/img/annotator-icon-sprite.png
NiukeJavaGongchengshiQiuzhiJingyanFenxiang20212022Fix1/img/apple-touch-icon.png
NiukeJavaGongchengshiQiuzhiJingyanFenxiang20212022Fix1/img/cancelfullscreen.png
NiukeJavaGongchengshiQiuzhiJingyanFenxiang20212022Fix1/img/close.png
NiukeJavaGongchengshiQiuzhiJingyanFenxiang20212022Fix1/img/fullscreen.png
NiukeJavaGongchengshiQiuzhiJingyanFenxiang20212022Fix1/img/loader.gif
NiukeJavaGongchengshiQiuzhiJingyanFenxiang20212022Fix1/img/menu-icon.png
NiukeJavaGongchengshiQiuzhiJingyanFenxiang20212022Fix1/img/save.png
NiukeJavaGongchengshiQiuzhiJingyanFenxiang20212022Fix1/img/saved.png
NiukeJavaGongchengshiQiuzhiJingyanFenxiang20212022Fix1/img/settings-s.png
niuke_java_gongchengshi_qiuzhi_jingyan_fenxiang_2021_2022_fix1-2025.3.25.0.dist-info/METADATA
niuke_java_gongchengshi_qiuzhi_jingyan_fenxiang_2021_2022_fix1-2025.3.25.0.dist-info/WHEEL
niuke_java_gongchengshi_qiuzhi_jingyan_fenxiang_2021_2022_fix1-2025.3.25.0.dist-info/entry_points.txt
niuke_java_gongchengshi_qiuzhi_jingyan_fenxiang_2021_2022_fix1-2025.3.25.0.dist-info/top_level.txt
niuke_java_gongchengshi_qiuzhi_jingyan_fenxiang_2021_2022_fix1-2025.3.25.0.dist-info/RECORD
